UE_OLED/__init__.py
UE_OLED/ssd1306.py
unitOled-0.3.dist-info/LICENSE
unitOled-0.3.dist-info/METADATA
unitOled-0.3.dist-info/WHEEL
unitOled-0.3.dist-info/top_level.txt
unitOled-0.3.dist-info/RECORD
