Metadata-Version: 2.1
Name: unitOled
Version: 0.3
Summary: i2c ssd1306 display driver for micropython
Home-page: https://github.com/Cesarbautista10/ISE_SSD1306/archive/refs/tags/v0.3.tar.gz
Author: Master
Author-email: cesar.bautista@uelectronics.com
License: MIT
License-File: LICENSE
